[
  {
    "all_emails_homepage": null,
    "home_phone": null,
    "all_phones_homepage": null,
    "last_name": "",
    "id": null,
    "fax": null,
    "email_3": null,
    "py/object": "models.contact.Contact",
    "work_phone": null,
    "address": "",
    "email_2": null,
    "first_name": "",
    "mobile_phone": "",
    "email_1": ""
  },
  {
    "all_emails_homepage": null,
    "home_phone": "+7161330",
    "all_phones_homepage": null,
    "last_name": "ON s2K IHYl",
    "id": null,
    "fax": "+1290686",
    "email_3": "THQ42K@LXmRS.co.uk",
    "py/object": "models.contact.Contact",
    "work_phone": "+466886",
    "address": "dTgWQeJm 4Os Ee3 pm\nj1ypUhKP\nHfGxpuSd 1 Hg Sz",
    "email_2": "lFr@yPM.de",
    "first_name": "bvRy5JOWx",
    "mobile_phone": "+5204642777",
    "email_1": "1pU8tkz@oAdCrp6.com"
  },
  {
    "all_emails_homepage": null,
    "home_phone": "+98548071",
    "all_phones_homepage": null,
    "last_name": "Gpim8GFVg",
    "id": null,
    "fax": "+412160",
    "email_3": "J@lO.tv",
    "py/object": "models.contact.Contact",
    "work_phone": "+50411525",
    "address": "s8gQ\nG9Oi grdyys2WY\nY081QbOj t4N 5mA",
    "email_2": "NK3@jTAjP9ke.ua",
    "first_name": "Y",
    "mobile_phone": "+4449361",
    "email_1": "1IRboX@AKrAz.co.uk"
  },
  {
    "all_emails_homepage": null,
    "home_phone": "+1958510836",
    "all_phones_homepage": null,
    "last_name": "G71E c",
    "id": null,
    "fax": "+928214765",
    "email_3": "SlV@CH6ZPz.co.uk",
    "py/object": "models.contact.Contact",
    "work_phone": "+97802924123",
    "address": "7KorYnvtFIzW\nNxlxzTlBcoCEm2H2Z a\nxZEo5CDdBst",
    "email_2": "nUq@OHDYnMQpR.gov",
    "first_name": "CTqv",
    "mobile_phone": "+828705",
    "email_1": "uRlN@nwtn.eu"
  },
  {
    "all_emails_homepage": null,
    "home_phone": "+0795811",
    "all_phones_homepage": null,
    "last_name": "erIJ",
    "id": null,
    "fax": "+89504781455",
    "email_3": "yHCj34k@hfF.ua",
    "py/object": "models.contact.Contact",
    "work_phone": "+230839",
    "address": "pkMnPk 2Lrf\nwz02Db8n\nKWICs",
    "email_2": "nPJ6@NhFE1.tv",
    "first_name": "gy7vnfC",
    "mobile_phone": "+9861421876",
    "email_1": "CxSLNhM@de2Joa5.co.uk"
  },
  {
    "all_emails_homepage": null,
    "home_phone": "+502713",
    "all_phones_homepage": null,
    "last_name": "M91WbEWgEt1 Q",
    "id": null,
    "fax": "+08880829875",
    "email_3": "YKbxIt@URHHm.eu",
    "py/object": "models.contact.Contact",
    "work_phone": "+7815895698",
    "address": "KBNu0z\nKQrw0 E4Ckk\nlqegg1DXTq 18NjGkZ",
    "email_2": "RypkNY@VhZxGx.eu",
    "first_name": "ftl",
    "mobile_phone": "+82885786779",
    "email_1": "xqeirgD@3T2gIjIL.tv"
  }
]